ghostbase/__init__.py
ghostbase/main.py
ghostbase-1.2.6.dist-info/METADATA
ghostbase-1.2.6.dist-info/WHEEL
ghostbase-1.2.6.dist-info/top_level.txt
ghostbase-1.2.6.dist-info/RECORD
