Metadata-Version: 2.1
Name: ghostbase
Version: 1.2.6
Summary: SelfHosted DB
Home-page: https://github.com/CyberZenDev/ghostbase
Author: CyberZenDev
Author-email: cyberzendev@gmail.com
License: MIT
Keywords: flask sqlite database
Classifier: Development Status :: 5 - Production/Stable
Classifier: Intended Audience :: Developers
Classifier: License :: OSI Approved :: MIT License
Classifier: Programming Language :: Python :: 3
Classifier: Programming Language :: Python :: 3.6
Classifier: Programming Language :: Python :: 3.7
Classifier: Programming Language :: Python :: 3.8
Classifier: Programming Language :: Python :: 3.9
Requires-Dist: requests
